tencent/__init__.py
tencent/base.py
tencent/constants.py
tencent/contrib/__init__.py
tencent/contrib/api/__init__.py
tencent/contrib/api/dialogue_visualization_api.py
tencent/contrib/api/stock_price_api.py
tencent/contrib/wechat/__init__.py
tencent/contrib/wechat/receive.py
tencent/contrib/wechat/reply.py
tencent/contrib/wechat/wechat_api.py
tencent/contrib/wechat/wechat_constants.py
tencent/data/__init__.py
tencent/data/greeting/__init__.py
tencent/data/greeting/ponyma_icon.txt
tencent/data/greeting/tencent_icon.txt
tencent/utils/__init__.py
tencent/utils/agent_utils.py
tencent/utils/data_utils.py
tencent-1.0.5.dist-info/METADATA
tencent-1.0.5.dist-info/WHEEL
tencent-1.0.5.dist-info/top_level.txt
tencent-1.0.5.dist-info/RECORD
