Metadata-Version: 2.1
Name: tencent
Version: 1.0.5
Summary: Contributed API Collections of Tencent Product and Services, such as Wechat Public Account Backend Automatic Reply, Calling OpenAI Agent to Use Tencent Service,etc.
Author-email: dingo0927@126.com
Project-URL: repository, https://github.com/AI-Hub-Admin/tencent
Project-URL: homepage, http://www.deepnlp.org/blog?category=tencent
Keywords: tencent,Wechat,QQ
Classifier: Development Status :: 3 - Alpha
Classifier: Intended Audience :: Developers
Classifier: Topic :: Software Development :: Build Tools
Classifier: License :: OSI Approved :: MIT License
Requires-Python: >=3.4
Requires-Dist: FinanceAgent >=0.0.2
Requires-Dist: requests >=2.17.0
Requires-Dist: importlib-resources >=6.4.0
Provides-Extra: dev
Requires-Dist: flask >=2.0.0 ; extra == 'dev'
Provides-Extra: test
Requires-Dist: flask >=2.0.0 ; extra == 'test'
